ppylex/__init__.py
ppylex/lex.py
ppylex-0.0.2.dist-info/LICENSE
ppylex-0.0.2.dist-info/METADATA
ppylex-0.0.2.dist-info/WHEEL
ppylex-0.0.2.dist-info/top_level.txt
ppylex-0.0.2.dist-info/RECORD
