Metadata-Version: 2.1
Name: ppylex
Version: 0.0.2
Summary: An feature extraction algorithm
Home-page: UNKNOWN
Author: jnddd
Author-email: 122296743@qq.com
License: MIT Licence
Platform: any
Requires-Dist: numpy
